odoo/addons/web_widget_one2many_product_picker_sale_stock/README.rst
odoo/addons/web_widget_one2many_product_picker_sale_stock/__init__.py
odoo/addons/web_widget_one2many_product_picker_sale_stock/__manifest__.py
odoo/addons/web_widget_one2many_product_picker_sale_stock/i18n/web_widget_one2many_product_picker_sale_stock.pot
odoo/addons/web_widget_one2many_product_picker_sale_stock/readme/CONTRIBUTORS.rst
odoo/addons/web_widget_one2many_product_picker_sale_stock/readme/DESCRIPTION.rst
odoo/addons/web_widget_one2many_product_picker_sale_stock/readme/USAGE.rst
odoo/addons/web_widget_one2many_product_picker_sale_stock/static/description/icon.png
odoo/addons/web_widget_one2many_product_picker_sale_stock/static/description/index.html
odoo/addons/web_widget_one2many_product_picker_sale_stock/static/src/js/views/abstract_view.js
odoo/addons/web_widget_one2many_product_picker_sale_stock/static/src/js/views/One2ManyProductPicker/record.js
odoo/addons/web_widget_one2many_product_picker_sale_stock/static/src/js/views/One2ManyProductPicker/renderer.js
odoo/addons/web_widget_one2many_product_picker_sale_stock/static/src/js/widgets/field_one2many_product_picker.js
odoo/addons/web_widget_one2many_product_picker_sale_stock/static/src/scss/one2many_product_picker.scss
odoo/addons/web_widget_one2many_product_picker_sale_stock/static/src/xml/one2many_product_picker.xml
odoo/addons/web_widget_one2many_product_picker_sale_stock/templates/assets.xml
odoo13_addon_web_widget_one2many_product_picker_sale_stock-13.0.1.0.1.dev3.dist-info/METADATA
odoo13_addon_web_widget_one2many_product_picker_sale_stock-13.0.1.0.1.dev3.dist-info/WHEEL
odoo13_addon_web_widget_one2many_product_picker_sale_stock-13.0.1.0.1.dev3.dist-info/top_level.txt
odoo13_addon_web_widget_one2many_product_picker_sale_stock-13.0.1.0.1.dev3.dist-info/RECORD
